CHANGELOG.md
LICENSE
MANIFEST.in
NOTICE
README.md
setup.cfg
setup.py
paypal2/__init__.py
paypal2/client.py
paypal2/hook.py
paypal2/misc.py
paypal2/utility.py
paypal2.egg-info/PKG-INFO
paypal2.egg-info/SOURCES.txt
paypal2.egg-info/dependency_links.txt
paypal2.egg-info/requires.txt
paypal2.egg-info/top_level.txt
paypal2/integration/__init__.py
paypal2/integration/deps.py
paypal2/integration/hook.py
paypal2/integration/order.py
paypal2/models/__init__.py
paypal2/models/common.py
paypal2/models/hook.py
paypal2/models/order.py
paypal2/models/payment.py
paypal2/models/plan.py
paypal2/models/product.py
paypal2/models/subscription.py
requirements/base.in
requirements/base.txt
requirements/test.in
requirements/test.txt