Metadata-Version: 2.1
Name: paypal2
Version: 0.5.0
Summary: Opinionated asyncio Paypal server-side integration SDK
Home-page: https://github.com/Traktormaster/paypal2
Author: Nándor Mátravölgyi
Author-email: nandor.matra@gmail.com
License: Apache 2.0
Classifier: Programming Language :: Python :: 3
Classifier: Programming Language :: Python :: 3.10
Classifier: Programming Language :: Python :: 3.11
Classifier: Programming Language :: Python :: 3.12
Classifier: Programming Language :: Python :: Implementation :: CPython
Classifier: Intended Audience :: Developers
Classifier: License :: OSI Approved :: Apache Software License
Requires-Python: >=3.10
License-File: LICENSE
License-File: NOTICE
Requires-Dist: aiohttp
Requires-Dist: certifi
Requires-Dist: pycryptodome
Requires-Dist: pydantic>=2
Requires-Dist: ttldict2
Provides-Extra: test
Requires-Dist: fastapi; extra == "test"
Requires-Dist: pytest; extra == "test"
Requires-Dist: pytest-asyncio; extra == "test"
Requires-Dist: pytest-httpserver; extra == "test"
Requires-Dist: pytest-order; extra == "test"
Requires-Dist: pytest-selenium; extra == "test"
